digitalocean/__init__.py
digitalocean/constants.py
digitalocean/droplet.py
digitalocean/exceptions.py
digitalocean/image.py
digitalocean/interface.py
digitalocean/region.py
digitalocean/size.py
digitalocean/utils.py
digitalocean/window.py
digitalocean/networks/__init__.py
digitalocean/networks/v4.py
digitalocean/networks/v6.py
py_digitalocean-0.1.0.dist-info/LICENSE
py_digitalocean-0.1.0.dist-info/METADATA
py_digitalocean-0.1.0.dist-info/WHEEL
py_digitalocean-0.1.0.dist-info/top_level.txt
py_digitalocean-0.1.0.dist-info/RECORD
