Metadata-Version: 2.1
Name: py-digitalocean
Version: 0.1.0
Summary: Digital Ocean Python Library
Home-page: https://gitlab.com/camphotos/py-digitalocean
Author: Alan Chester
Author-email: amcheste@gmail.com
License: MIT
Platform: UNKNOWN
Classifier: Programming Language :: Python :: 3
Classifier: License :: OSI Approved :: MIT License
Classifier: Operating System :: OS Independent
Requires-Python: >=3.6
License-File: LICENSE
Requires-Dist: requests
